LICENSE.md
MANIFEST.in
README.rst
setup.py
bin/lxxl
bin/lxxl.authentication.admin
bin/lxxl.authentication.front
bin/lxxl.graph
bin/lxxl.wildbull
lxxl/__init__.py
lxxl.egg-info/PKG-INFO
lxxl.egg-info/SOURCES.txt
lxxl.egg-info/dependency_links.txt
lxxl.egg-info/requires.txt
lxxl.egg-info/top_level.txt
lxxl/conf/common.yml
lxxl/conf/storage.yml
lxxl/conf/dev/common.yml
lxxl/conf/dev/storage.yml
lxxl/conf/prod/common.yml
lxxl/conf/prod/storage.yml
lxxl/conf/routing/common.yml
lxxl/conf/routing/wildbull.yml
lxxl/conf/routing/authentication/admin.yml
lxxl/conf/routing/authentication/front.yml
lxxl/conf/routing/graph/activities.yml
lxxl/conf/routing/graph/categories.yml
lxxl/conf/routing/graph/revisions.yml
lxxl/conf/routing/graph/usergroups.yml
lxxl/conf/routing/graph/users.yml
lxxl/conf/snap/common.yml
lxxl/conf/snap/storage.yml
lxxl/lib/__init__.py
lxxl/lib/admin.py
lxxl/lib/app.py
lxxl/lib/auth.py
lxxl/lib/config.py
lxxl/lib/fb.py
lxxl/lib/flush.py
lxxl/lib/log.py
lxxl/lib/mailer.py
lxxl/lib/output.py
lxxl/lib/router.py
lxxl/lib/storage.py
lxxl/lib/utils.py
lxxl/model/__init__.py
lxxl/model/users.py
lxxl/model/auth/__init__.py
lxxl/model/auth/access.py
lxxl/model/auth/users.py
lxxl/services/__init__.py
lxxl/services/authentication/__init__.py
lxxl/services/authentication/admin/__init__.py
lxxl/services/authentication/admin/key.py
lxxl/services/authentication/admin/user.py
lxxl/services/authentication/front/__init__.py
lxxl/services/authentication/front/anonymous.py
lxxl/services/authentication/front/generic.py
lxxl/services/authentication/front/void.py
lxxl/services/common/__init__.py
lxxl/services/common/prob.py
lxxl/services/graph/__init__.py
lxxl/services/graph/activities.py
lxxl/services/graph/categories.py
lxxl/services/graph/revisions.py
lxxl/services/graph/usergroups.py
lxxl/services/graph/users.py
lxxl/services/graph/users/__init__.py
lxxl/services/graph/users/account.py
lxxl/services/graph/users/activities.py
lxxl/services/graph/users/avatar.py
lxxl/services/graph/users/preferences.py
lxxl/services/graph/users/profile.py
lxxl/services/graph/users/settings.py
lxxl/services/wildbull/__init__.py
