Metadata-Version: 1.0
Name: lxxl
Version: 0.0.3
Summary: LxxL Web Services
Home-page: http://education-numerique.github.com/api/
Author: Education Numerique
Author-email: tech@webitup.fr
License: ### GNU AFFERO GENERAL PUBLIC LICENSE
